textbsr/__init__.py
textbsr/textbsr.py
textbsr/checkpoints/__init__.py
textbsr/models/TextEnhancement.py
textbsr/models/__init__.py
textbsr/utils/__init__.py
textbsr/utils/utils_image.py
textbsr-0.1.12.dist-info/LICENSE
textbsr-0.1.12.dist-info/METADATA
textbsr-0.1.12.dist-info/WHEEL
textbsr-0.1.12.dist-info/entry_points.txt
textbsr-0.1.12.dist-info/top_level.txt
textbsr-0.1.12.dist-info/RECORD
